setup.py
ajaxmiddleware/__init__.py
ajaxmiddleware/decorators.py
ajaxmiddleware/middleware.py
ajaxmiddleware/mixins.py
ajaxmiddleware/views.py
django_ajaxmiddleware.egg-info/PKG-INFO
django_ajaxmiddleware.egg-info/SOURCES.txt
django_ajaxmiddleware.egg-info/dependency_links.txt
django_ajaxmiddleware.egg-info/not-zip-safe
django_ajaxmiddleware.egg-info/requires.txt
django_ajaxmiddleware.egg-info/top_level.txt
testapp/project/__init__.py
testapp/project/forms.py
testapp/project/models.py
testapp/project/urls.py
testapp/project/views.py
testapp/project/tests/__init__.py
testapp/project/tests/views_tests.py