Metadata-Version: 1.0
Name: django-ajaxmiddleware
Version: 0.2.1
Summary: django middleware to handle ajax requests really easily
Home-page: http://github.com/Fandekasp/django-ajaxmiddleware
Author: Adrien Lemaire
Author-email: lemaire.adrien@gmail.com
License: UNKNOWN
Keywords: django ajax json
Platform: UNKNOWN
Classifier: Development Status :: 4 - Beta
Classifier: License :: OSI Approved :: BSD License
Classifier: Framework :: Django
Classifier: Intended Audience :: Developers
Classifier: Operating System :: OS Independent
Classifier: Programming Language :: Python
Classifier: Topic :: Software Development :: Libraries :: Python Modules
